pybrige/__init__.py
pybrige/core/__init__.py
pybrige/core/config.py
pybrige/core/logging.py
pybrige/decorators/__init__.py
pybrige/decorators/robustness.py
pybrige/decorators/timing.py
pybrige/utils/__init__.py
pybrige/utils/dicts.py
pybrige/utils/formatting.py
pybrige/utils/io.py
pybrige/utils/text.py
pybrige-0.5.1.dist-info/METADATA
pybrige-0.5.1.dist-info/WHEEL
pybrige-0.5.1.dist-info/licenses/LICENSE
pybrige-0.5.1.dist-info/RECORD
