Metadata-Version: 2.4
Name: pybrige
Version: 0.5.1
Summary: Um toolkit de produtividade para desenvolvedores em Python
Project-URL: Homepage, https://github.com/juliobrige/pybrige
Project-URL: Bug Tracker, https://github.com/juliobrige/pybrige/issues
Project-URL: Documentation, https://github.com/juliobrige/pybrige/blob/main/README.md
Author-email: Julio Benjamim Bernardo Brige <juliobenjamimbernardo36@gmail.com>
License: MIT
License-File: LICENSE
Requires-Python: >=3.8
Requires-Dist: python-dotenv
Requires-Dist: rich
